<?xml version="1.0" encoding="UTF-8"?>
<objects serializationModel="Studio.02.02.00">
	<object class="AudioFile" id="{65056b1f-c7fb-4780-b959-114c2ab80b4d}">
		<property name="assetPath">
			<value>Music/Mississippi Mover - Everet Almond.mp3</value>
		</property>
		<property name="isStreaming">
			<value>true</value>
		</property>
		<property name="frequencyInKHz">
			<value>44.0999985</value>
		</property>
		<property name="channelCount">
			<value>2</value>
		</property>
		<property name="length">
			<value>173.94938775510204</value>
		</property>
		<relationship name="masterAssetFolder">
			<destination>{e37b6da7-be7e-4fee-98f1-69703ffb0033}</destination>
		</relationship>
	</object>
</objects>
